random_wiki/__init__.py
random_wiki/__main__.py
random_wiki-0.3.0.dist-info/METADATA
random_wiki-0.3.0.dist-info/WHEEL
random_wiki-0.3.0.dist-info/entry_points.txt
random_wiki-0.3.0.dist-info/RECORD
